{
  "__data_type": "DLG ",
  "DelayEntry": {
    "type": "dword",
    "value": 0
  },
  "DelayReply": {
    "type": "dword",
    "value": 0
  },
  "EndConverAbort": {
    "type": "resref",
    "value": "nw_walk_wp"
  },
  "EndConversation": {
    "type": "resref",
    "value": "nw_walk_wp"
  },
  "EntryList": {
    "type": "list",
    "value": [
      {
        "__struct_id": 0,
        "Animation": {
          "type": "dword",
          "value": 0
        },
        "AnimLoop": {
          "type": "byte",
          "value": 1
        },
        "Comment": {
          "type": "cexostring",
          "value": ""
        },
        "Delay": {
          "type": "dword",
          "value": 4294967295
        },
        "Quest": {
          "type": "cexostring",
          "value": ""
        },
        "RepliesList": {
          "type": "list",
          "value": [
            {
              "__struct_id": 0,
              "Active": {
                "type": "resref",
                "value": ""
              },
              "Index": {
                "type": "dword",
                "value": 2
              },
              "IsChild": {
                "type": "byte",
                "value": 0
              }
            },
            {
              "__struct_id": 1,
              "Active": {
                "type": "resref",
                "value": ""
              },
              "Index": {
                "type": "dword",
                "value": 1
              },
              "IsChild": {
                "type": "byte",
                "value": 0
              }
            },
            {
              "__struct_id": 2,
              "Active": {
                "type": "resref",
                "value": ""
              },
              "Index": {
                "type": "dword",
                "value": 0
              },
              "IsChild": {
                "type": "byte",
                "value": 0
              }
            }
          ]
        },
        "Script": {
          "type": "resref",
          "value": ""
        },
        "Sound": {
          "type": "resref",
          "value": ""
        },
        "Speaker": {
          "type": "cexostring",
          "value": ""
        },
        "Text": {
          "type": "cexolocstring",
          "value": {
            "0": "So, you want to play some cards? The game is Par'Un Gom, you do know how to play don't you?"
          }
        }
      },
      {
        "__struct_id": 1,
        "Animation": {
          "type": "dword",
          "value": 0
        },
        "AnimLoop": {
          "type": "byte",
          "value": 1
        },
        "Comment": {
          "type": "cexostring",
          "value": ""
        },
        "Delay": {
          "type": "dword",
          "value": 4294967295
        },
        "Quest": {
          "type": "cexostring",
          "value": ""
        },
        "RepliesList": {
          "type": "list",
          "value": [
            {
              "__struct_id": 0,
              "Active": {
                "type": "resref",
                "value": ""
              },
              "Index": {
                "type": "dword",
                "value": 2
              },
              "IsChild": {
                "type": "byte",
                "value": 1
              },
              "LinkComment": {
                "type": "cexostring",
                "value": ""
              }
            },
            {
              "__struct_id": 1,
              "Active": {
                "type": "resref",
                "value": ""
              },
              "Index": {
                "type": "dword",
                "value": 0
              },
              "IsChild": {
                "type": "byte",
                "value": 1
              },
              "LinkComment": {
                "type": "cexostring",
                "value": ""
              }
            }
          ]
        },
        "Script": {
          "type": "resref",
          "value": ""
        },
        "Sound": {
          "type": "resref",
          "value": ""
        },
        "Speaker": {
          "type": "cexostring",
          "value": ""
        },
        "Text": {
          "type": "cexolocstring",
          "value": {
            "0": "The Par'Un Gom deck contains 9 cards, each with a single value from 1 to 9. Both the dealer and the player are dealt 3 of these cards. The objective is to get the sum of your cards closer to 15 than the dealer without going over 15.\n\nOnce dealt your cards you will have the option of trading one of your cards for a randomly drawn card from the remainder of the deck. The card you give back goes back into the deck, where the dealer then has a chance to trade a card. In the event of a tie, the dealer wins."
          }
        }
      },
      {
        "__struct_id": 2,
        "Animation": {
          "type": "dword",
          "value": 0
        },
        "AnimLoop": {
          "type": "byte",
          "value": 1
        },
        "Comment": {
          "type": "cexostring",
          "value": ""
        },
        "Delay": {
          "type": "dword",
          "value": 4294967295
        },
        "Quest": {
          "type": "cexostring",
          "value": ""
        },
        "RepliesList": {
          "type": "list",
          "value": [
            {
              "__struct_id": 0,
              "Active": {
                "type": "resref",
                "value": ""
              },
              "Index": {
                "type": "dword",
                "value": 3
              },
              "IsChild": {
                "type": "byte",
                "value": 0
              }
            }
          ]
        },
        "Script": {
          "type": "resref",
          "value": "pug_gmbl_listen"
        },
        "Sound": {
          "type": "resref",
          "value": ""
        },
        "Speaker": {
          "type": "cexostring",
          "value": ""
        },
        "Text": {
          "type": "cexolocstring",
          "value": {
            "0": "How much would you like to wager? Tell me the amount you want to bet .."
          }
        }
      },
      {
        "__struct_id": 3,
        "Animation": {
          "type": "dword",
          "value": 0
        },
        "AnimLoop": {
          "type": "byte",
          "value": 1
        },
        "Comment": {
          "type": "cexostring",
          "value": ""
        },
        "Delay": {
          "type": "dword",
          "value": 4294967295
        },
        "Quest": {
          "type": "cexostring",
          "value": ""
        },
        "RepliesList": {
          "type": "list",
          "value": [
            {
              "__struct_id": 0,
              "Active": {
                "type": "resref",
                "value": ""
              },
              "Index": {
                "type": "dword",
                "value": 7
              },
              "IsChild": {
                "type": "byte",
                "value": 0
              }
            },
            {
              "__struct_id": 1,
              "Active": {
                "type": "resref",
                "value": ""
              },
              "Index": {
                "type": "dword",
                "value": 6
              },
              "IsChild": {
                "type": "byte",
                "value": 0
              }
            },
            {
              "__struct_id": 2,
              "Active": {
                "type": "resref",
                "value": ""
              },
              "Index": {
                "type": "dword",
                "value": 5
              },
              "IsChild": {
                "type": "byte",
                "value": 0
              }
            },
            {
              "__struct_id": 3,
              "Active": {
                "type": "resref",
                "value": ""
              },
              "Index": {
                "type": "dword",
                "value": 4
              },
              "IsChild": {
                "type": "byte",
                "value": 0
              }
            }
          ]
        },
        "Script": {
          "type": "resref",
          "value": ""
        },
        "Sound": {
          "type": "resref",
          "value": ""
        },
        "Speaker": {
          "type": "cexostring",
          "value": ""
        },
        "Text": {
          "type": "cexolocstring",
          "value": {
            "0": "<CUSTOM22456>"
          }
        }
      },
      {
        "__struct_id": 4,
        "Animation": {
          "type": "dword",
          "value": 0
        },
        "AnimLoop": {
          "type": "byte",
          "value": 1
        },
        "Comment": {
          "type": "cexostring",
          "value": ""
        },
        "Delay": {
          "type": "dword",
          "value": 4294967295
        },
        "Quest": {
          "type": "cexostring",
          "value": ""
        },
        "RepliesList": {
          "type": "list",
          "value": [
            {
              "__struct_id": 0,
              "Active": {
                "type": "resref",
                "value": ""
              },
              "Index": {
                "type": "dword",
                "value": 8
              },
              "IsChild": {
                "type": "byte",
                "value": 1
              },
              "LinkComment": {
                "type": "cexostring",
                "value": ""
              }
            }
          ]
        },
        "Script": {
          "type": "resref",
          "value": ""
        },
        "Sound": {
          "type": "resref",
          "value": ""
        },
        "Speaker": {
          "type": "cexostring",
          "value": ""
        },
        "Text": {
          "type": "cexolocstring",
          "value": {
            "0": "You have decided to keep your cards. Next the dealer will decide what to do."
          }
        }
      },
      {
        "__struct_id": 5,
        "Animation": {
          "type": "dword",
          "value": 0
        },
        "AnimLoop": {
          "type": "byte",
          "value": 1
        },
        "Comment": {
          "type": "cexostring",
          "value": ""
        },
        "Delay": {
          "type": "dword",
          "value": 4294967295
        },
        "Quest": {
          "type": "cexostring",
          "value": ""
        },
        "RepliesList": {
          "type": "list",
          "value": [
            {
              "__struct_id": 0,
              "Active": {
                "type": "resref",
                "value": ""
              },
              "Index": {
                "type": "dword",
                "value": 8
              },
              "IsChild": {
                "type": "byte",
                "value": 0
              }
            }
          ]
        },
        "Script": {
          "type": "resref",
          "value": ""
        },
        "Sound": {
          "type": "resref",
          "value": ""
        },
        "Speaker": {
          "type": "cexostring",
          "value": ""
        },
        "Text": {
          "type": "cexolocstring",
          "value": {
            "0": "<CUSTOM22451>"
          }
        }
      },
      {
        "__struct_id": 6,
        "Animation": {
          "type": "dword",
          "value": 0
        },
        "AnimLoop": {
          "type": "byte",
          "value": 1
        },
        "Comment": {
          "type": "cexostring",
          "value": ""
        },
        "Delay": {
          "type": "dword",
          "value": 4294967295
        },
        "Quest": {
          "type": "cexostring",
          "value": ""
        },
        "RepliesList": {
          "type": "list",
          "value": [
            {
              "__struct_id": 0,
              "Active": {
                "type": "resref",
                "value": ""
              },
              "Index": {
                "type": "dword",
                "value": 9
              },
              "IsChild": {
                "type": "byte",
                "value": 0
              }
            }
          ]
        },
        "Script": {
          "type": "resref",
          "value": ""
        },
        "Sound": {
          "type": "resref",
          "value": ""
        },
        "Speaker": {
          "type": "cexostring",
          "value": ""
        },
        "Text": {
          "type": "cexolocstring",
          "value": {
            "0": "<CUSTOM22452>"
          }
        }
      },
      {
        "__struct_id": 7,
        "Animation": {
          "type": "dword",
          "value": 0
        },
        "AnimLoop": {
          "type": "byte",
          "value": 1
        },
        "Comment": {
          "type": "cexostring",
          "value": ""
        },
        "Delay": {
          "type": "dword",
          "value": 4294967295
        },
        "Quest": {
          "type": "cexostring",
          "value": ""
        },
        "RepliesList": {
          "type": "list",
          "value": [
            {
              "__struct_id": 0,
              "Active": {
                "type": "resref",
                "value": ""
              },
              "Index": {
                "type": "dword",
                "value": 11
              },
              "IsChild": {
                "type": "byte",
                "value": 0
              }
            },
            {
              "__struct_id": 1,
              "Active": {
                "type": "resref",
                "value": ""
              },
              "Index": {
                "type": "dword",
                "value": 10
              },
              "IsChild": {
                "type": "byte",
                "value": 0
              }
            }
          ]
        },
        "Script": {
          "type": "resref",
          "value": ""
        },
        "Sound": {
          "type": "resref",
          "value": ""
        },
        "Speaker": {
          "type": "cexostring",
          "value": ""
        },
        "Text": {
          "type": "cexolocstring",
          "value": {
            "0": "<CUSTOM22453>"
          }
        }
      }
    ]
  },
  "NumWords": {
    "type": "dword",
    "value": 184
  },
  "PreventZoomIn": {
    "type": "byte",
    "value": 0
  },
  "ReplyList": {
    "type": "list",
    "value": [
      {
        "__struct_id": 0,
        "Animation": {
          "type": "dword",
          "value": 0
        },
        "AnimLoop": {
          "type": "byte",
          "value": 1
        },
        "Comment": {
          "type": "cexostring",
          "value": ""
        },
        "Delay": {
          "type": "dword",
          "value": 4294967295
        },
        "EntriesList": {
          "type": "list",
          "value": []
        },
        "Quest": {
          "type": "cexostring",
          "value": ""
        },
        "Script": {
          "type": "resref",
          "value": ""
        },
        "Sound": {
          "type": "resref",
          "value": ""
        },
        "Text": {
          "type": "cexolocstring",
          "value": {
            "0": "Sorry, nevermind"
          }
        }
      },
      {
        "__struct_id": 1,
        "Animation": {
          "type": "dword",
          "value": 0
        },
        "AnimLoop": {
          "type": "byte",
          "value": 1
        },
        "Comment": {
          "type": "cexostring",
          "value": ""
        },
        "Delay": {
          "type": "dword",
          "value": 4294967295
        },
        "EntriesList": {
          "type": "list",
          "value": [
            {
              "__struct_id": 0,
              "Active": {
                "type": "resref",
                "value": ""
              },
              "Index": {
                "type": "dword",
                "value": 1
              },
              "IsChild": {
                "type": "byte",
                "value": 0
              }
            }
          ]
        },
        "Quest": {
          "type": "cexostring",
          "value": ""
        },
        "Script": {
          "type": "resref",
          "value": ""
        },
        "Sound": {
          "type": "resref",
          "value": ""
        },
        "Text": {
          "type": "cexolocstring",
          "value": {
            "0": "No, what are the rules?"
          }
        }
      },
      {
        "__struct_id": 2,
        "Animation": {
          "type": "dword",
          "value": 0
        },
        "AnimLoop": {
          "type": "byte",
          "value": 1
        },
        "Comment": {
          "type": "cexostring",
          "value": ""
        },
        "Delay": {
          "type": "dword",
          "value": 4294967295
        },
        "EntriesList": {
          "type": "list",
          "value": [
            {
              "__struct_id": 0,
              "Active": {
                "type": "resref",
                "value": ""
              },
              "Index": {
                "type": "dword",
                "value": 2
              },
              "IsChild": {
                "type": "byte",
                "value": 0
              }
            }
          ]
        },
        "Quest": {
          "type": "cexostring",
          "value": ""
        },
        "Script": {
          "type": "resref",
          "value": ""
        },
        "Sound": {
          "type": "resref",
          "value": ""
        },
        "Text": {
          "type": "cexolocstring",
          "value": {
            "0": "Of course, let's play!"
          }
        }
      },
      {
        "__struct_id": 3,
        "Animation": {
          "type": "dword",
          "value": 0
        },
        "AnimLoop": {
          "type": "byte",
          "value": 1
        },
        "Comment": {
          "type": "cexostring",
          "value": ""
        },
        "Delay": {
          "type": "dword",
          "value": 4294967295
        },
        "EntriesList": {
          "type": "list",
          "value": [
            {
              "__struct_id": 0,
              "Active": {
                "type": "resref",
                "value": "pug_gmbl_ifbet"
              },
              "Index": {
                "type": "dword",
                "value": 3
              },
              "IsChild": {
                "type": "byte",
                "value": 0
              }
            }
          ]
        },
        "Quest": {
          "type": "cexostring",
          "value": ""
        },
        "Script": {
          "type": "resref",
          "value": "pug_gmbl_bet"
        },
        "Sound": {
          "type": "resref",
          "value": ""
        },
        "Text": {
          "type": "cexolocstring",
          "value": {
            "0": "Continue."
          }
        }
      },
      {
        "__struct_id": 4,
        "Animation": {
          "type": "dword",
          "value": 0
        },
        "AnimLoop": {
          "type": "byte",
          "value": 1
        },
        "Comment": {
          "type": "cexostring",
          "value": ""
        },
        "Delay": {
          "type": "dword",
          "value": 4294967295
        },
        "EntriesList": {
          "type": "list",
          "value": [
            {
              "__struct_id": 0,
              "Active": {
                "type": "resref",
                "value": ""
              },
              "Index": {
                "type": "dword",
                "value": 4
              },
              "IsChild": {
                "type": "byte",
                "value": 0
              }
            }
          ]
        },
        "Quest": {
          "type": "cexostring",
          "value": ""
        },
        "Script": {
          "type": "resref",
          "value": ""
        },
        "Sound": {
          "type": "resref",
          "value": ""
        },
        "Text": {
          "type": "cexolocstring",
          "value": {
            "0": "Keep Cards"
          }
        }
      },
      {
        "__struct_id": 5,
        "Animation": {
          "type": "dword",
          "value": 0
        },
        "AnimLoop": {
          "type": "byte",
          "value": 1
        },
        "Comment": {
          "type": "cexostring",
          "value": ""
        },
        "Delay": {
          "type": "dword",
          "value": 4294967295
        },
        "EntriesList": {
          "type": "list",
          "value": [
            {
              "__struct_id": 0,
              "Active": {
                "type": "resref",
                "value": ""
              },
              "Index": {
                "type": "dword",
                "value": 5
              },
              "IsChild": {
                "type": "byte",
                "value": 1
              },
              "LinkComment": {
                "type": "cexostring",
                "value": ""
              }
            }
          ]
        },
        "Quest": {
          "type": "cexostring",
          "value": ""
        },
        "Script": {
          "type": "resref",
          "value": "pug_gmbl_trade3"
        },
        "Sound": {
          "type": "resref",
          "value": ""
        },
        "Text": {
          "type": "cexolocstring",
          "value": {
            "0": "<CUSTOM22459>"
          }
        }
      },
      {
        "__struct_id": 6,
        "Animation": {
          "type": "dword",
          "value": 0
        },
        "AnimLoop": {
          "type": "byte",
          "value": 1
        },
        "Comment": {
          "type": "cexostring",
          "value": ""
        },
        "Delay": {
          "type": "dword",
          "value": 4294967295
        },
        "EntriesList": {
          "type": "list",
          "value": [
            {
              "__struct_id": 0,
              "Active": {
                "type": "resref",
                "value": ""
              },
              "Index": {
                "type": "dword",
                "value": 5
              },
              "IsChild": {
                "type": "byte",
                "value": 1
              },
              "LinkComment": {
                "type": "cexostring",
                "value": ""
              }
            }
          ]
        },
        "Quest": {
          "type": "cexostring",
          "value": ""
        },
        "Script": {
          "type": "resref",
          "value": "pug_gmbl_trade2"
        },
        "Sound": {
          "type": "resref",
          "value": ""
        },
        "Text": {
          "type": "cexolocstring",
          "value": {
            "0": "<CUSTOM22458>"
          }
        }
      },
      {
        "__struct_id": 7,
        "Animation": {
          "type": "dword",
          "value": 0
        },
        "AnimLoop": {
          "type": "byte",
          "value": 1
        },
        "Comment": {
          "type": "cexostring",
          "value": ""
        },
        "Delay": {
          "type": "dword",
          "value": 4294967295
        },
        "EntriesList": {
          "type": "list",
          "value": [
            {
              "__struct_id": 0,
              "Active": {
                "type": "resref",
                "value": ""
              },
              "Index": {
                "type": "dword",
                "value": 5
              },
              "IsChild": {
                "type": "byte",
                "value": 0
              }
            }
          ]
        },
        "Quest": {
          "type": "cexostring",
          "value": ""
        },
        "Script": {
          "type": "resref",
          "value": "pug_gmbl_trade1"
        },
        "Sound": {
          "type": "resref",
          "value": ""
        },
        "Text": {
          "type": "cexolocstring",
          "value": {
            "0": "<CUSTOM22457>"
          }
        }
      },
      {
        "__struct_id": 8,
        "Animation": {
          "type": "dword",
          "value": 0
        },
        "AnimLoop": {
          "type": "byte",
          "value": 1
        },
        "Comment": {
          "type": "cexostring",
          "value": ""
        },
        "Delay": {
          "type": "dword",
          "value": 4294967295
        },
        "EntriesList": {
          "type": "list",
          "value": [
            {
              "__struct_id": 0,
              "Active": {
                "type": "resref",
                "value": ""
              },
              "Index": {
                "type": "dword",
                "value": 6
              },
              "IsChild": {
                "type": "byte",
                "value": 0
              }
            }
          ]
        },
        "Quest": {
          "type": "cexostring",
          "value": ""
        },
        "Script": {
          "type": "resref",
          "value": "pug_gmbl_dlrgo"
        },
        "Sound": {
          "type": "resref",
          "value": ""
        },
        "Text": {
          "type": "cexolocstring",
          "value": {
            "0": "Continue."
          }
        }
      },
      {
        "__struct_id": 9,
        "Animation": {
          "type": "dword",
          "value": 0
        },
        "AnimLoop": {
          "type": "byte",
          "value": 1
        },
        "Comment": {
          "type": "cexostring",
          "value": ""
        },
        "Delay": {
          "type": "dword",
          "value": 4294967295
        },
        "EntriesList": {
          "type": "list",
          "value": [
            {
              "__struct_id": 0,
              "Active": {
                "type": "resref",
                "value": ""
              },
              "Index": {
                "type": "dword",
                "value": 7
              },
              "IsChild": {
                "type": "byte",
                "value": 0
              }
            }
          ]
        },
        "Quest": {
          "type": "cexostring",
          "value": ""
        },
        "Script": {
          "type": "resref",
          "value": "pug_gmbl_endgame"
        },
        "Sound": {
          "type": "resref",
          "value": ""
        },
        "Text": {
          "type": "cexolocstring",
          "value": {
            "0": "Continue."
          }
        }
      },
      {
        "__struct_id": 10,
        "Animation": {
          "type": "dword",
          "value": 0
        },
        "AnimLoop": {
          "type": "byte",
          "value": 1
        },
        "Comment": {
          "type": "cexostring",
          "value": ""
        },
        "Delay": {
          "type": "dword",
          "value": 4294967295
        },
        "EntriesList": {
          "type": "list",
          "value": []
        },
        "Quest": {
          "type": "cexostring",
          "value": ""
        },
        "Script": {
          "type": "resref",
          "value": ""
        },
        "Sound": {
          "type": "resref",
          "value": ""
        },
        "Text": {
          "type": "cexolocstring",
          "value": {
            "0": "No, goodbye."
          }
        }
      },
      {
        "__struct_id": 11,
        "Animation": {
          "type": "dword",
          "value": 0
        },
        "AnimLoop": {
          "type": "byte",
          "value": 1
        },
        "Comment": {
          "type": "cexostring",
          "value": ""
        },
        "Delay": {
          "type": "dword",
          "value": 4294967295
        },
        "EntriesList": {
          "type": "list",
          "value": [
            {
              "__struct_id": 0,
              "Active": {
                "type": "resref",
                "value": ""
              },
              "Index": {
                "type": "dword",
                "value": 2
              },
              "IsChild": {
                "type": "byte",
                "value": 1
              },
              "LinkComment": {
                "type": "cexostring",
                "value": ""
              }
            }
          ]
        },
        "Quest": {
          "type": "cexostring",
          "value": ""
        },
        "Script": {
          "type": "resref",
          "value": ""
        },
        "Sound": {
          "type": "resref",
          "value": ""
        },
        "Text": {
          "type": "cexolocstring",
          "value": {
            "0": "Sure, deal the cards."
          }
        }
      }
    ]
  },
  "StartingList": {
    "type": "list",
    "value": [
      {
        "__struct_id": 0,
        "Active": {
          "type": "resref",
          "value": ""
        },
        "Index": {
          "type": "dword",
          "value": 0
        }
      }
    ]
  }
}
