{
  "__data_type": "DLG ",
  "DelayEntry": {
    "type": "dword",
    "value": 0
  },
  "DelayReply": {
    "type": "dword",
    "value": 0
  },
  "EndConverAbort": {
    "type": "resref",
    "value": "nw_walk_wp"
  },
  "EndConversation": {
    "type": "resref",
    "value": "nw_walk_wp"
  },
  "EntryList": {
    "type": "list",
    "value": [
      {
        "__struct_id": 0,
        "Animation": {
          "type": "dword",
          "value": 0
        },
        "AnimLoop": {
          "type": "byte",
          "value": 1
        },
        "Comment": {
          "type": "cexostring",
          "value": ""
        },
        "Delay": {
          "type": "dword",
          "value": 4294967295
        },
        "Quest": {
          "type": "cexostring",
          "value": ""
        },
        "RepliesList": {
          "type": "list",
          "value": [
            {
              "__struct_id": 0,
              "Active": {
                "type": "resref",
                "value": "pug_qst_ifrapbdg"
              },
              "Index": {
                "type": "dword",
                "value": 2
              },
              "IsChild": {
                "type": "byte",
                "value": 0
              }
            },
            {
              "__struct_id": 1,
              "Active": {
                "type": "resref",
                "value": ""
              },
              "Index": {
                "type": "dword",
                "value": 1
              },
              "IsChild": {
                "type": "byte",
                "value": 0
              }
            },
            {
              "__struct_id": 2,
              "Active": {
                "type": "resref",
                "value": ""
              },
              "Index": {
                "type": "dword",
                "value": 0
              },
              "IsChild": {
                "type": "byte",
                "value": 0
              }
            }
          ]
        },
        "Script": {
          "type": "resref",
          "value": ""
        },
        "Sound": {
          "type": "resref",
          "value": ""
        },
        "Speaker": {
          "type": "cexostring",
          "value": ""
        },
        "Text": {
          "type": "cexolocstring",
          "value": {
            "0": "<Class>, we have a problem with a group of criminals in the crimson corridor known as the Raptors. If you can bring me proof that you have quelled these thugs I will compensate you for your efforts."
          }
        }
      },
      {
        "__struct_id": 1,
        "Animation": {
          "type": "dword",
          "value": 0
        },
        "AnimLoop": {
          "type": "byte",
          "value": 1
        },
        "Comment": {
          "type": "cexostring",
          "value": ""
        },
        "Delay": {
          "type": "dword",
          "value": 4294967295
        },
        "Quest": {
          "type": "cexostring",
          "value": ""
        },
        "RepliesList": {
          "type": "list",
          "value": []
        },
        "Script": {
          "type": "resref",
          "value": ""
        },
        "Sound": {
          "type": "resref",
          "value": ""
        },
        "Speaker": {
          "type": "cexostring",
          "value": ""
        },
        "Text": {
          "type": "cexolocstring",
          "value": {
            "0": "Good work, here is your reward."
          }
        }
      },
      {
        "__struct_id": 2,
        "Animation": {
          "type": "dword",
          "value": 0
        },
        "AnimLoop": {
          "type": "byte",
          "value": 1
        },
        "Comment": {
          "type": "cexostring",
          "value": ""
        },
        "Delay": {
          "type": "dword",
          "value": 4294967295
        },
        "Quest": {
          "type": "cexostring",
          "value": ""
        },
        "RepliesList": {
          "type": "list",
          "value": [
            {
              "__struct_id": 0,
              "Active": {
                "type": "resref",
                "value": "pug_qst_ifbosded"
              },
              "Index": {
                "type": "dword",
                "value": 4
              },
              "IsChild": {
                "type": "byte",
                "value": 0
              }
            },
            {
              "__struct_id": 1,
              "Active": {
                "type": "resref",
                "value": ""
              },
              "Index": {
                "type": "dword",
                "value": 3
              },
              "IsChild": {
                "type": "byte",
                "value": 0
              }
            }
          ]
        },
        "Script": {
          "type": "resref",
          "value": ""
        },
        "Sound": {
          "type": "resref",
          "value": ""
        },
        "Speaker": {
          "type": "cexostring",
          "value": ""
        },
        "Text": {
          "type": "cexolocstring",
          "value": {
            "0": "There is one more thing I need you to do. The raptor overlord must be destroyed. Once he is dead come and see me and I will have a great reward for you."
          }
        }
      },
      {
        "__struct_id": 3,
        "Animation": {
          "type": "dword",
          "value": 0
        },
        "AnimLoop": {
          "type": "byte",
          "value": 1
        },
        "Comment": {
          "type": "cexostring",
          "value": ""
        },
        "Delay": {
          "type": "dword",
          "value": 4294967295
        },
        "Quest": {
          "type": "cexostring",
          "value": ""
        },
        "RepliesList": {
          "type": "list",
          "value": [
            {
              "__struct_id": 0,
              "Active": {
                "type": "resref",
                "value": ""
              },
              "Index": {
                "type": "dword",
                "value": 8
              },
              "IsChild": {
                "type": "byte",
                "value": 0
              }
            },
            {
              "__struct_id": 1,
              "Active": {
                "type": "resref",
                "value": ""
              },
              "Index": {
                "type": "dword",
                "value": 7
              },
              "IsChild": {
                "type": "byte",
                "value": 0
              }
            },
            {
              "__struct_id": 2,
              "Active": {
                "type": "resref",
                "value": ""
              },
              "Index": {
                "type": "dword",
                "value": 6
              },
              "IsChild": {
                "type": "byte",
                "value": 0
              }
            },
            {
              "__struct_id": 3,
              "Active": {
                "type": "resref",
                "value": ""
              },
              "Index": {
                "type": "dword",
                "value": 5
              },
              "IsChild": {
                "type": "byte",
                "value": 0
              }
            }
          ]
        },
        "Script": {
          "type": "resref",
          "value": ""
        },
        "Sound": {
          "type": "resref",
          "value": ""
        },
        "Speaker": {
          "type": "cexostring",
          "value": ""
        },
        "Text": {
          "type": "cexolocstring",
          "value": {
            "0": "Great work! For your reward I will allow you to choose your own starship. Please choose one of the following ships."
          }
        }
      },
      {
        "__struct_id": 4,
        "Animation": {
          "type": "dword",
          "value": 0
        },
        "AnimLoop": {
          "type": "byte",
          "value": 1
        },
        "Comment": {
          "type": "cexostring",
          "value": ""
        },
        "Delay": {
          "type": "dword",
          "value": 4294967295
        },
        "Quest": {
          "type": "cexostring",
          "value": ""
        },
        "RepliesList": {
          "type": "list",
          "value": []
        },
        "Script": {
          "type": "resref",
          "value": ""
        },
        "Sound": {
          "type": "resref",
          "value": ""
        },
        "Speaker": {
          "type": "cexostring",
          "value": ""
        },
        "Text": {
          "type": "cexolocstring",
          "value": {
            "0": "Here you go, the galaxy is now your playground."
          }
        }
      },
      {
        "__struct_id": 5,
        "Animation": {
          "type": "dword",
          "value": 0
        },
        "AnimLoop": {
          "type": "byte",
          "value": 1
        },
        "Comment": {
          "type": "cexostring",
          "value": ""
        },
        "Delay": {
          "type": "dword",
          "value": 4294967295
        },
        "Quest": {
          "type": "cexostring",
          "value": ""
        },
        "RepliesList": {
          "type": "list",
          "value": []
        },
        "Script": {
          "type": "resref",
          "value": ""
        },
        "Sound": {
          "type": "resref",
          "value": ""
        },
        "Speaker": {
          "type": "cexostring",
          "value": ""
        },
        "Text": {
          "type": "cexolocstring",
          "value": {
            "0": "Excellent work! Take some time off and relax."
          }
        }
      },
      {
        "__struct_id": 6,
        "Animation": {
          "type": "dword",
          "value": 0
        },
        "AnimLoop": {
          "type": "byte",
          "value": 1
        },
        "Comment": {
          "type": "cexostring",
          "value": ""
        },
        "Delay": {
          "type": "dword",
          "value": 4294967295
        },
        "Quest": {
          "type": "cexostring",
          "value": ""
        },
        "RepliesList": {
          "type": "list",
          "value": []
        },
        "Script": {
          "type": "resref",
          "value": ""
        },
        "Sound": {
          "type": "resref",
          "value": ""
        },
        "Speaker": {
          "type": "cexostring",
          "value": ""
        },
        "Text": {
          "type": "cexolocstring",
          "value": {
            "0": "Hello <Sir/Madam>, nothing to report!"
          }
        }
      }
    ]
  },
  "NumWords": {
    "type": "dword",
    "value": 154
  },
  "PreventZoomIn": {
    "type": "byte",
    "value": 0
  },
  "ReplyList": {
    "type": "list",
    "value": [
      {
        "__struct_id": 0,
        "Animation": {
          "type": "dword",
          "value": 0
        },
        "AnimLoop": {
          "type": "byte",
          "value": 1
        },
        "Comment": {
          "type": "cexostring",
          "value": ""
        },
        "Delay": {
          "type": "dword",
          "value": 4294967295
        },
        "EntriesList": {
          "type": "list",
          "value": []
        },
        "Quest": {
          "type": "cexostring",
          "value": ""
        },
        "Script": {
          "type": "resref",
          "value": ""
        },
        "Sound": {
          "type": "resref",
          "value": ""
        },
        "Text": {
          "type": "cexolocstring",
          "value": {
            "0": "I'll think about it."
          }
        }
      },
      {
        "__struct_id": 1,
        "Animation": {
          "type": "dword",
          "value": 0
        },
        "AnimLoop": {
          "type": "byte",
          "value": 1
        },
        "Comment": {
          "type": "cexostring",
          "value": ""
        },
        "Delay": {
          "type": "dword",
          "value": 4294967295
        },
        "EntriesList": {
          "type": "list",
          "value": []
        },
        "Quest": {
          "type": "cexostring",
          "value": ""
        },
        "Script": {
          "type": "resref",
          "value": ""
        },
        "Sound": {
          "type": "resref",
          "value": ""
        },
        "Text": {
          "type": "cexolocstring",
          "value": {
            "0": "Yes, sir! I'll get right to it!"
          }
        }
      },
      {
        "__struct_id": 2,
        "Animation": {
          "type": "dword",
          "value": 0
        },
        "AnimLoop": {
          "type": "byte",
          "value": 1
        },
        "Comment": {
          "type": "cexostring",
          "value": ""
        },
        "Delay": {
          "type": "dword",
          "value": 4294967295
        },
        "EntriesList": {
          "type": "list",
          "value": [
            {
              "__struct_id": 0,
              "Active": {
                "type": "resref",
                "value": ""
              },
              "Index": {
                "type": "dword",
                "value": 1
              },
              "IsChild": {
                "type": "byte",
                "value": 0
              }
            }
          ]
        },
        "Quest": {
          "type": "cexostring",
          "value": ""
        },
        "Script": {
          "type": "resref",
          "value": "pug_qst_raptrgiv"
        },
        "Sound": {
          "type": "resref",
          "value": ""
        },
        "Text": {
          "type": "cexolocstring",
          "value": {
            "0": "I have a raptor badge to turn in"
          }
        }
      },
      {
        "__struct_id": 3,
        "Animation": {
          "type": "dword",
          "value": 0
        },
        "AnimLoop": {
          "type": "byte",
          "value": 1
        },
        "Comment": {
          "type": "cexostring",
          "value": ""
        },
        "Delay": {
          "type": "dword",
          "value": 4294967295
        },
        "EntriesList": {
          "type": "list",
          "value": []
        },
        "Quest": {
          "type": "cexostring",
          "value": ""
        },
        "Script": {
          "type": "resref",
          "value": ""
        },
        "Sound": {
          "type": "resref",
          "value": ""
        },
        "Text": {
          "type": "cexolocstring",
          "value": {
            "0": "Yes, sir!"
          }
        }
      },
      {
        "__struct_id": 4,
        "Animation": {
          "type": "dword",
          "value": 0
        },
        "AnimLoop": {
          "type": "byte",
          "value": 1
        },
        "Comment": {
          "type": "cexostring",
          "value": ""
        },
        "Delay": {
          "type": "dword",
          "value": 4294967295
        },
        "EntriesList": {
          "type": "list",
          "value": [
            {
              "__struct_id": 0,
              "Active": {
                "type": "resref",
                "value": ""
              },
              "Index": {
                "type": "dword",
                "value": 3
              },
              "IsChild": {
                "type": "byte",
                "value": 0
              }
            }
          ]
        },
        "Quest": {
          "type": "cexostring",
          "value": ""
        },
        "Script": {
          "type": "resref",
          "value": ""
        },
        "Sound": {
          "type": "resref",
          "value": ""
        },
        "Text": {
          "type": "cexolocstring",
          "value": {
            "0": "I have killed the Criminal Overlord."
          }
        }
      },
      {
        "__struct_id": 5,
        "Animation": {
          "type": "dword",
          "value": 0
        },
        "AnimLoop": {
          "type": "byte",
          "value": 1
        },
        "Comment": {
          "type": "cexostring",
          "value": ""
        },
        "Delay": {
          "type": "dword",
          "value": 4294967295
        },
        "EntriesList": {
          "type": "list",
          "value": [
            {
              "__struct_id": 0,
              "Active": {
                "type": "resref",
                "value": ""
              },
              "Index": {
                "type": "dword",
                "value": 4
              },
              "IsChild": {
                "type": "byte",
                "value": 1
              },
              "LinkComment": {
                "type": "cexostring",
                "value": ""
              }
            }
          ]
        },
        "Quest": {
          "type": "cexostring",
          "value": ""
        },
        "Script": {
          "type": "resref",
          "value": "pug_qst_lambda"
        },
        "Sound": {
          "type": "resref",
          "value": ""
        },
        "Text": {
          "type": "cexolocstring",
          "value": {
            "0": "Lambda Transport."
          }
        }
      },
      {
        "__struct_id": 6,
        "Animation": {
          "type": "dword",
          "value": 0
        },
        "AnimLoop": {
          "type": "byte",
          "value": 1
        },
        "Comment": {
          "type": "cexostring",
          "value": ""
        },
        "Delay": {
          "type": "dword",
          "value": 4294967295
        },
        "EntriesList": {
          "type": "list",
          "value": [
            {
              "__struct_id": 0,
              "Active": {
                "type": "resref",
                "value": ""
              },
              "Index": {
                "type": "dword",
                "value": 4
              },
              "IsChild": {
                "type": "byte",
                "value": 1
              },
              "LinkComment": {
                "type": "cexostring",
                "value": ""
              }
            }
          ]
        },
        "Quest": {
          "type": "cexostring",
          "value": ""
        },
        "Script": {
          "type": "resref",
          "value": "pug_qst_tiebmber"
        },
        "Sound": {
          "type": "resref",
          "value": ""
        },
        "Text": {
          "type": "cexolocstring",
          "value": {
            "0": "TIE Bomber."
          }
        }
      },
      {
        "__struct_id": 7,
        "Animation": {
          "type": "dword",
          "value": 0
        },
        "AnimLoop": {
          "type": "byte",
          "value": 1
        },
        "Comment": {
          "type": "cexostring",
          "value": ""
        },
        "Delay": {
          "type": "dword",
          "value": 4294967295
        },
        "EntriesList": {
          "type": "list",
          "value": [
            {
              "__struct_id": 0,
              "Active": {
                "type": "resref",
                "value": ""
              },
              "Index": {
                "type": "dword",
                "value": 4
              },
              "IsChild": {
                "type": "byte",
                "value": 1
              },
              "LinkComment": {
                "type": "cexostring",
                "value": ""
              }
            }
          ]
        },
        "Quest": {
          "type": "cexostring",
          "value": ""
        },
        "Script": {
          "type": "resref",
          "value": "pug_qst_tieintrc"
        },
        "Sound": {
          "type": "resref",
          "value": ""
        },
        "Text": {
          "type": "cexolocstring",
          "value": {
            "0": "TIE Interceptor."
          }
        }
      },
      {
        "__struct_id": 8,
        "Animation": {
          "type": "dword",
          "value": 0
        },
        "AnimLoop": {
          "type": "byte",
          "value": 1
        },
        "Comment": {
          "type": "cexostring",
          "value": ""
        },
        "Delay": {
          "type": "dword",
          "value": 4294967295
        },
        "EntriesList": {
          "type": "list",
          "value": [
            {
              "__struct_id": 0,
              "Active": {
                "type": "resref",
                "value": ""
              },
              "Index": {
                "type": "dword",
                "value": 4
              },
              "IsChild": {
                "type": "byte",
                "value": 0
              }
            }
          ]
        },
        "Quest": {
          "type": "cexostring",
          "value": ""
        },
        "Script": {
          "type": "resref",
          "value": "pug_qst_tiefghtr"
        },
        "Sound": {
          "type": "resref",
          "value": ""
        },
        "Text": {
          "type": "cexolocstring",
          "value": {
            "0": "TIE Fighter."
          }
        }
      }
    ]
  },
  "StartingList": {
    "type": "list",
    "value": [
      {
        "__struct_id": 0,
        "Active": {
          "type": "resref",
          "value": "pug_qst_lvl8max"
        },
        "Index": {
          "type": "dword",
          "value": 6
        }
      },
      {
        "__struct_id": 1,
        "Active": {
          "type": "resref",
          "value": "pug_qst_raptrdon"
        },
        "Index": {
          "type": "dword",
          "value": 5
        }
      },
      {
        "__struct_id": 2,
        "Active": {
          "type": "resref",
          "value": "pug_qst_raptrmax"
        },
        "Index": {
          "type": "dword",
          "value": 2
        }
      },
      {
        "__struct_id": 3,
        "Active": {
          "type": "resref",
          "value": "grey_isempire"
        },
        "Index": {
          "type": "dword",
          "value": 0
        }
      }
    ]
  }
}
