{
  "__data_type": "UTI ",
  "AddCost": {
    "type": "dword",
    "value": 59
  },
  "BaseItem": {
    "type": "int",
    "value": 202
  },
  "Charges": {
    "type": "byte",
    "value": 0
  },
  "Comment": {
    "type": "cexostring",
    "value": ""
  },
  "Cost": {
    "type": "dword",
    "value": 61
  },
  "Cursed": {
    "type": "byte",
    "value": 0
  },
  "DescIdentified": {
    "type": "cexolocstring",
    "value": {
      "0": "Coffee is a non-alcoholic beverage that is most often served extremely hot and made from a specific type of bean. Coffee can be prepared and dispensed from a coffee machine, and is usually served in a coffee cup. Emperor Palpatine owns farms on various planets that provide the beans to produce high quality coffee and vine-coffee, solely for the use of his Court."
    }
  },
  "Description": {
    "type": "cexolocstring",
    "value": {
      "0": "Coffee is a non-alcoholic beverage that is most often served extremely hot and made from a specific type of bean. Coffee can be prepared and dispensed from a coffee machine, and is usually served in a coffee cup. Emperor Palpatine owns farms on various planets that provide the beans to produce high quality coffee and vine-coffee, solely for the use of his Court."
    }
  },
  "Identified": {
    "type": "byte",
    "value": 1
  },
  "LocalizedName": {
    "type": "cexolocstring",
    "value": {
      "0": "Coffee"
    }
  },
  "ModelPart1": {
    "type": "byte",
    "value": 11
  },
  "ModelPart2": {
    "type": "byte",
    "value": 21
  },
  "ModelPart3": {
    "type": "byte",
    "value": 11
  },
  "PaletteID": {
    "type": "byte",
    "value": 24
  },
  "Plot": {
    "type": "byte",
    "value": 0
  },
  "PropertiesList": {
    "type": "list",
    "value": []
  },
  "StackSize": {
    "type": "word",
    "value": 1
  },
  "Stolen": {
    "type": "byte",
    "value": 0
  },
  "Tag": {
    "type": "cexostring",
    "value": "Coffee"
  },
  "TemplateResRef": {
    "type": "resref",
    "value": "coffee"
  }
}
